Workbook

Sheet Summary
A1: Offer Comparison Summary
A3: Offer | B3: Expected Final Price | C3: Buyer Broker Fee | D3: Seller Transfer Tax | E3: Net Before Listing Fee | F3: Risk Rating | G3: Quick Notes
A4: ='Offer Matrix'!A2&" - "&'Offer Matrix'!B2 -> Offer 1 - Ethan J. Hahn and Christina Hahn | B4: ='Offer Matrix'!F2 -> 660000 | C4: ='Offer Matrix'!Q2 -> 16500 | D4: ='Offer Matrix'!T2 -> 6600 | E4: ='Offer Matrix'!Z2 -> 636900 | F4: ='Offer Matrix'!AC2 -> 3 | G4: Strong personal/gift support, but seller-paid buyer broker fee reduces net.
A5: ='Offer Matrix'!A3&" - "&'Offer Matrix'!B3 -> Offer 2 - Steven Mendes and Eva Mendes | B5: ='Offer Matrix'!F3 -> 650000 | C5: ='Offer Matrix'!Q3 -> 0 | D5: ='Offer Matrix'!T3 -> 0 | E5: ='Offer Matrix'!Z3 -> 650000 | F5: ='Offer Matrix'!AC3 -> 1 | G5: Lowest max price but cleanest terms: cash/no mortgage, waived inspections, buyer pays seller transfer tax. Need to confirm no Buyer Broker fee
A6: ='Offer Matrix'!A4&" - "&'Offer Matrix'!B4 -> Offer 3 - Shannon Henry and Petri Santala | B6: ='Offer Matrix'!F4 -> 686000 | C6: ='Offer Matrix'!Q4 -> 17150 | D6: ='Offer Matrix'!T4 -> 6860 | E6: ='Offer Matrix'!Z4 -> 661990 | F6: ='Offer Matrix'!AC4 -> 4 | G6: Highest possible gross price, but mortgage contingency and $11k appraisal gap cap need scrutiny.
A7: ='Offer Matrix'!A5&" - "&'Offer Matrix'!B5 -> Offer 4 - Christopher J. Campis and Maria Lourdes Abigaile Campis | B7: ='Offer Matrix'!F5 -> 665700 | C7: ='Offer Matrix'!Q5 -> 16642.5 | D7: ='Offer Matrix'!T5 -> 6657 | E7: ='Offer Matrix'!Z5 -> 642400.5 | F7: ='Offer Matrix'!AC5 -> 2 | G7: Cash/no mortgage and waived inspections; net is reduced by buyer broker fee and normal seller transfer tax.
A9: Best By Category
A10: Highest expected final price | B10: =INDEX(A4:A7,MATCH(MAX(B4:B7),B4:B7,0)) -> Offer 3 - Shannon Henry and Petri Santala | D10: Next step | E10: Ask agent for official net sheets and confirmation of buyer broker compensation for each offer.
A11: Highest net before listing fee | B11: =INDEX(A4:A7,MATCH(MAX(E4:E7),E4:E7,0)) -> Offer 3 - Shannon Henry and Petri Santala
A12: Lowest risk rating | B12: =INDEX(A4:A7,MATCH(MIN(F4:F7),F4:F7,0)) -> Offer 2 - Steven Mendes and Eva Mendes
A13: Cleanest financing/appraisal risk | B13: =INDEX(A5:A8,MATCH(MIN(F5:F8),F5:F8,0)) -> Offer 2 - Steven Mendes and Eva Mendes
A14: Biggest clarification needed | B14: Offer 3 appraisal/financing and Offer 1 typo

Sheet Offer Matrix
A1: Offer | B1: Buyer | C1: Base Purchase Price | D1: Escalation Cap | E1: Escalation Increment | F1: Expected Final Price | G1: Deposit / Earnest Money | H1: Financing Type | I1: Mortgage Contingency | J1: Loan Amount / LTV | K1: Appraisal Contingency | L1: Appraisal Gap Coverage | M1: Minimum Appraisal Needed | N1: Inspection Contingencies | O1: Seller Concessions / Buyer Broker | P1: Buyer Broker Fee Rate | Q1: Buyer Broker Fee Cost | R1: Transfer Tax Terms | S1: Seller Transfer Tax Rate | T1: Seller Transfer Tax Cost | U1: Settlement Date | V1: Extensions / Timing Flexibility | W1: Sale-of-Home Contingency | X1: Included Items | Y1: Excluded Items Issue | Z1: Net Before Listing Fee | AA1: Estimated Listing Fee | AB1: Estimated Net After Listing Fee | AC1: Risk Rating | AD1: Questions / Counterpoints
A2: Offer 1 | B2: Ethan J. Hahn and Christina Hahn | C2: 640000 | D2: 660000 | E2: 2000 | F2: 660000 | G2: 12000 | H2: Mortgage possible; large gift letter provided | I2: Waived | J2: Not specified in visible terms; gift letter says $660k available | K2: No ACA checked in ASR/PEA | L2: 0 | M2: =IF(L2>0,F2-L2,"N/A") -> N/A | N2: All standard inspections waived | O2: Seller pays buyer broker 2.5%; no closing-cost assist shown | P2: 0.025 | Q2: =F2*P2 -> 16500 | R2: Split normally; no buyer payment of seller side stated | S2: 0.01 | T2: =F2*S2 -> 6600 | U2: 46185 | V2: No special extension term seen | W2: None seen | X2: Washer, dryer, dishwasher, stove, refrigerator | Y2: All mirrors except bathroom mirrors remain; dining room chandelier; bird feeders/houses/baths; armillary sundial | Z2: =F2-Q2-T2 -> 636900 | AA2: =F2*Assumptions!$B$2 -> 16500 | AB2: =Z2-AA2 -> 620400 | AC2: 3 | AD2: Escalation cap appears typed as $660,0000 in the PEA; ask agent to correct/confirm. Buyer-broker fee materially reduces net.
A3: Offer 2 | B3: Steven Mendes and Eva Mendes | C3: 640000 | D3: 650000 | E3: 1200 | F3: 650000 | G3: 10000 | H3: Cash / no mortgage financing | I3: Not applicable; buyer will not obtain mortgage financing | J3: N/A | K3: No ACA checked in ASR/PEA | L3: 0 | M3: =IF(L3>0,F3-L3,"N/A") -> N/A | N3: All standard inspections waived | O3: No buyer broker fee or closing-cost assist shown | P3: 0 | Q3: =F3*P3 -> 0 | R3: Buyer pays seller's side of transfer tax | S3: 0 | T3: =F3*S3 -> 0 | U3: 46183 | V3: No special extension term seen | W3: None seen | X3: All appliances in as-is condition at no additional monetary value | Y3: All mirrors except upstairs bathroom mirrors; dining room chandelier; garage EV charger negotiable; exterior bird items and sundial | Z3: =F3-Q3-T3 -> 650000 | AA3: =F3*Assumptions!$B$2 -> 16250 | AB3: =Z3-AA3 -> 633750 | AC3: 1 | AD3: Lowest cap of the three, but cleanest seller economics and lowest financing/appraisal risk. Need to confirm buyer broker fee.
A4: Offer 3 | B4: Shannon Henry and Petri Santala | C4: 656000 | D4: 686000 | F4: 686000 | G4: 20000 | H4: Conventional mortgage | I4: Elected | J4: $548,800 first mortgage / 80% LTV | K4: Custom additional term; ACA not checked | L4: 11000 | M4: =IF(L4>0,F4-L4,"N/A") -> 675000 | N4: All standard inspections waived | O4: Seller pays buyer broker 2.5%; no closing-cost assist shown | P4: 0.025 | Q4: =F4*P4 -> 17150 | R4: Split normally; no buyer payment of seller side stated | S4: 0.01 | T4: =F4*S4 -> 6860 | U4: 46203 | V4: Buyers agree to extend 30 days as needed | W4: None seen | X4: Washer/dryer, fridge, oven | Y4: No exclusions typed in agreement section reviewed | Z4: =F4-Q4-T4 -> 661990 | AA4: =F4*Assumptions!$B$2 -> 17150 | AB4: =Z4-AA4 -> 644840 | AC4: 4 | AD4: Highest possible gross price, but financing is contingent and appraisal gap is capped at $11k. At $686k, appraisal likely needs to be at least $675k.
A5: Offer 4 | B5: Christopher J. Campis and Maria Lourdes Abigaile Campis | C5: 651600 | D5: 665700 | E5: 5251 | F5: 665700 | G5: 15000 | H5: Cash / no mortgage financing; proof of funds and designated family funds included | I5: Not applicable; buyer will not obtain mortgage financing | J5: N/A | K5: No ACA checked in ASR/PEA | L5: 0 | M5: =IF(L5>0,F5-L5,"N/A") -> N/A | N5: All standard inspections waived | O5: Seller pays buyer broker 2.5%; no closing-cost assist shown | P5: 0.025 | Q5: =F5*P5 -> 16642.5 | R5: Split normally; no buyer payment of seller side stated | S5: 0.01 | T5: =F5*S5 -> 6657 | U5: 46175 | V5: Settlement date marked flexible | W5: None seen | X5: All appliances in as-is condition | Y5: All mirrors except upstairs bathroom mirrors; dining room chandelier; garage EV charger; exterior bird items and sundial | Z5: =F5-Q5-T5 -> 642400.5 | AA5: =F5*Assumptions!$B$2 -> 16642.5 | AB5: =Z5-AA5 -> 625758 | AC5: 2 | AD5: Strong cash/no-financing structure and waived inspections, but seller-paid buyer broker fee and seller transfer tax reduce net.

Sheet Assumptions
A1: Assumption | B1: Value
A2: Listing broker fee rate | B2: 0.025
A3: Seller-side transfer tax rate | B3: 0.01
A4: Offer 3 escalation cap per user summary | B4: 686000
A5: Offer 3 appraisal gap cap | B5: 11000
A6: Default risk scale | B6: 1 = lower risk, 5 = higher risk
A7: Notes | B7: Edit the blue assumption cells if your agent gives different numbers.

Sheet Source Notes
A1: Offer | B1: File / Source | C1: Key Values Used | D1: Caveats
A2: Offer 1 | B2: Offer 1 - Updated Offer!.pdf; Offer 1 - Gift Letter from James Hahn.pdf | C2: Base $640k; escalation +$2k to apparent $660k cap; deposit $12k; waived mortgage contingency; inspections waived; seller pays buyer broker 2.5%; settlement 6/12/2026; gift letter states $660k available. | D2: PEA cap appears typoed as $660,0000. No ACA checked in reviewed agreement.
A3: Offer 2 | B3: Offer 2.pdf | C3: Base $640k; escalation +$1.2k to $650k cap; deposit $10k; cash/no mortgage financing; inspections waived; buyer pays seller-side transfer tax; settlement 6/10/2026. | D3: Acceptance-date field appears amended/duplicative; confirm with agent.
A4: Offer 3 | B4: Standard Agreement For The Sale of Real Estate (PAR ASR) (14).pdf plus user summary | C4: Base $656k; user-provided escalation cap $686k; deposit $20k; conventional financing contingency elected; loan $548,800 at 80% LTV; inspections waived; buyer broker 2.5%; $11k appraisal gap clause; settlement 6/30/2026. | D4: PEA itself was referenced but not in the reviewed 14-page PDF. Additional term says appraisal gap, but ACA is not checked.
A5: Offer 4 | B5: fwdofferforclarencedrivefrompattieheinerealtor folder: 1847 Clarence Dr. AOS.pdf; 1847 Clarence Dr., Price Escalation.pdf; Buyers Financial Information (2).pdf; Designation of Funds.pdf | C5: Base $651,600; escalation +$5,251 to $665,700 cap; deposit $15k; no mortgage financing; inspections waived; buyer broker 2.5%; no appraisal addendum checked; settlement 6/2/2026 flexible; buyer financial statement shows $1.13M+ assets and designated funds letter. | D5: AOS and PEA are scanned, so key fields were read from rendered pages. Transfer taxes default to normal split because no alternate term was typed.
